composio_openai_agents/__init__.py
composio_openai_agents/provider.py
composio_openai_agents/py.typed
composio_openai_agents-0.10.7.dist-info/METADATA
composio_openai_agents-0.10.7.dist-info/WHEEL
composio_openai_agents-0.10.7.dist-info/top_level.txt
composio_openai_agents-0.10.7.dist-info/RECORD
