Metadata-Version: 2.4
Name: composio-openai-agents
Version: 0.10.7
Summary: Use Composio to get array of strongly typed tools for OpenAI Agents
Home-page: https://github.com/ComposioHQ/composio
Author: Composio
Author-email: Composio <tech@composio.dev>
Project-URL: Homepage, https://github.com/ComposioHQ/composio
Classifier: Programming Language :: Python :: 3
Classifier: License :: OSI Approved :: Apache Software License
Classifier: Operating System :: OS Independent
Requires-Python: >=3.9,<4
Requires-Dist: openai-agents>=0.0.3
Requires-Dist: composio
Dynamic: author
Dynamic: home-page
Dynamic: requires-python
